pysparkling/__init__.py
pysparkling/accumulators.py
pysparkling/broadcast.py
pysparkling/cache_manager.py
pysparkling/context.py
pysparkling/exceptions.py
pysparkling/partition.py
pysparkling/rdd.py
pysparkling/samplers.py
pysparkling/stat_counter.py
pysparkling/task_context.py
pysparkling/utils.py
pysparkling/fileio/__init__.py
pysparkling/fileio/file.py
pysparkling/fileio/textfile.py
pysparkling/fileio/codec/__init__.py
pysparkling/fileio/codec/bz2.py
pysparkling/fileio/codec/codec.py
pysparkling/fileio/codec/gz.py
pysparkling/fileio/codec/lzma.py
pysparkling/fileio/codec/sevenz.py
pysparkling/fileio/codec/tar.py
pysparkling/fileio/codec/zip.py
pysparkling/fileio/fs/__init__.py
pysparkling/fileio/fs/file_system.py
pysparkling/fileio/fs/gs.py
pysparkling/fileio/fs/hdfs.py
pysparkling/fileio/fs/http.py
pysparkling/fileio/fs/local.py
pysparkling/fileio/fs/s3.py
pysparkling/streaming/__init__.py
pysparkling/streaming/context.py
pysparkling/streaming/dstream.py
pysparkling/streaming/filestream.py
pysparkling/streaming/queuestream.py
pysparkling/streaming/tcpstream.py
pysparkling/tests/__init__.py
pysparkling/tests/profile_textfile.py
pysparkling/tests/test_cache.py
pysparkling/tests/test_context.py
pysparkling/tests/test_multiprocessing.py
pysparkling/tests/test_rdd.py
pysparkling/tests/test_resolve_filenames.py
pysparkling/tests/test_sample.py
pysparkling/tests/test_stat_counter.py
pysparkling/tests/test_streaming_files.py
pysparkling/tests/test_streaming_queue.py
pysparkling/tests/test_streaming_tcp.py
pysparkling/tests/test_textFile.py
pysparkling-0.6.0.dist-info/LICENSE
pysparkling-0.6.0.dist-info/METADATA
pysparkling-0.6.0.dist-info/WHEEL
pysparkling-0.6.0.dist-info/entry_points.txt
pysparkling-0.6.0.dist-info/top_level.txt
pysparkling-0.6.0.dist-info/RECORD
