Metadata-Version: 2.1
Name: pysparkling
Version: 0.6.0
Summary: Pure Python implementation of the Spark RDD interface.
Home-page: https://github.com/svenkreiss/pysparkling
Author: Sven Kreiss
Author-email: me@svenkreiss.com
License: MIT
Platform: UNKNOWN
Classifier: Development Status :: 4 - Beta
Classifier: Intended Audience :: Developers
Classifier: Natural Language :: English
Classifier: License :: OSI Approved :: MIT License
Classifier: Operating System :: OS Independent
Classifier: Programming Language :: Python
Classifier: Programming Language :: Python :: 2.7
Classifier: Programming Language :: Python :: 3.4
Classifier: Programming Language :: Python :: 3.5
Classifier: Programming Language :: Python :: 3.6
Classifier: Programming Language :: Python :: Implementation :: PyPy
Requires-Dist: boto (>=2.36.0)
Requires-Dist: future (>=0.15)
Requires-Dist: requests (>=2.6.0)
Provides-Extra: hdfs
Requires-Dist: hdfs (>=2.0.0) ; extra == 'hdfs'
Provides-Extra: performance
Requires-Dist: matplotlib (>=1.5.3) ; extra == 'performance'
Provides-Extra: streaming
Requires-Dist: tornado (>=4.3) ; extra == 'streaming'
Provides-Extra: test
Requires-Dist: backports.tempfile (==1.0rc1) ; extra == 'test'
Requires-Dist: cloudpickle (>=0.1.0) ; extra == 'test'
Requires-Dist: futures (>=3.0.1) ; extra == 'test'
Requires-Dist: pylint ; extra == 'test'
Requires-Dist: memory-profiler (>=0.47) ; extra == 'test'
Requires-Dist: pytest ; extra == 'test'
Requires-Dist: tornado (>=4.3) ; extra == 'test'
